tls_regressor-0.1.2.dist-info/METADATA
tls_regressor-0.1.2.dist-info/WHEEL
tls_regressor.libs/libgfortran-5b574c8a.so.5
tls_regressor/tls.py
tls_regressor/__init__.py
tls_regressor/tls_regressor.cpython-311-x86_64-linux-gnu.so
tls_regressor-0.1.2.dist-info/RECORD
