Metadata-Version: 2.4
Name: tls_regressor
Version: 0.1.2
Classifier: Programming Language :: Python :: 3
Classifier: Programming Language :: Python :: 3.11
Classifier: Programming Language :: Rust
Classifier: License :: OSI Approved :: MIT License
Classifier: Operating System :: OS Independent
Requires-Dist: numpy>=1.20.0
Summary: Fast Total Least Squares regression using Rust backend
Author-email: connect0459 <connect0459@gmail.com>
Requires-Python: >=3.11
Project-URL: Homepage, https://github.com/connect0459/tls_regressor
Project-URL: Bug Tracker, https://github.com/connect0459/tls_regressor/issues
